coges/__init__.py
coges/coge.py
coges/di.py
coges/machine.py
coges/py.typed
coges-0.9.0.dist-info/LICENSE
coges-0.9.0.dist-info/WHEEL
coges-0.9.0.dist-info/METADATA
coges-0.9.0.dist-info/RECORD
