Metadata-Version: 2.1
Name: coges
Version: 0.9.0
Summary: Library for implementing non-linear behaviour and stream processing
License: MIT
Author: Jellyfish.tech
Author-email: manager@jellyfish.tech
Requires-Python: >=3.10,<4.0
Classifier: License :: OSI Approved :: MIT License
Classifier: Programming Language :: Python :: 3
Classifier: Programming Language :: Python :: 3.10
Classifier: Programming Language :: Python :: 3.11
Requires-Dist: loguru (>=0.7.2,<0.8.0)
